_tests/__init__.py
_tests/test_pput.py
_tests/test_snap.py
_tests/test_ssh_sync.py
zfs3backup/__init__.py
zfs3backup/config.py
zfs3backup/get.py
zfs3backup/pput.py
zfs3backup/s3_mp_cleanup.py
zfs3backup/snap.py
zfs3backup/ssh_sync.py
zfs3backup/zfs3backup.conf
zfs3backup-0.2.2.dist-info/LICENSE
zfs3backup-0.2.2.dist-info/METADATA
zfs3backup-0.2.2.dist-info/WHEEL
zfs3backup-0.2.2.dist-info/entry_points.txt
zfs3backup-0.2.2.dist-info/top_level.txt
zfs3backup-0.2.2.dist-info/RECORD
