Metadata-Version: 2.1
Name: zfs3backup
Version: 0.2.2
Summary: Backup ZFS snapshots to S3
Home-page: https://github.com/mmontagna/zfs3backup
Author: Marco Montagna
Author-email: marcojoemontagna@gmail.com
License: LICENSE
Keywords: ZFS backup
Platform: any
Classifier: Development Status :: 4 - Beta
Classifier: Environment :: Console
Classifier: License :: OSI Approved :: Apache Software License
Classifier: Topic :: System :: Archiving :: Backup
Classifier: Topic :: Utilities
Requires-Dist: boto3
